{"is_source_file": false, "format": "", "description": "", "external_files": [], "external_methods": [], "published": [], "classes": [], "methods": [], "calls": [], "search-terms": [], "state": 2, "file_id": 5, "knowledge_revision": 20, "git_revision": "3604fb4429aca6178e83f1ebbadc3be68dadee27", "ctags": [{"_type": "tag", "name": "App", "path": "/home/kavia/workspace/code-generation/notemaster-59166-59080/notes_frontend/src/app.d.ts", "pattern": "/^\tnamespace App {$/", "language": "TypeScript", "kind": "namespace"}], "hash": "78b56494b3f78d7f9bacda13678f159e", "format-version": 4, "code-base-name": "notes_frontend", "filename": "notes_frontend/src/app.d.ts", "revision_history": [{"20": "3604fb4429aca6178e83f1ebbadc3be68dadee27"}]}